[{"PLAYER_ID":"1631093","PLAYER_NAME":"Jaden Ivey","SEASON":"2023-24","SHOT_ZONE_BASIC":"Above the Break 3","actual_points":288,"actual_points_per_shot":1.0286,"league_expected_pps":1.1255,"player_expected_pps":1.0288,"shot_making_per_100":-9.6916,"player_adjusted_edge_per_100":-9.6657},{"PLAYER_ID":"1631093","PLAYER_NAME":"Jaden Ivey","SEASON":"2023-24","SHOT_ZONE_BASIC":"Backcourt","actual_points":0,"actual_points_per_shot":0.0,"league_expected_pps":0.0206,"player_expected_pps":0.0319,"shot_making_per_100":-2.0604,"player_adjusted_edge_per_100":1.1262},{"PLAYER_ID":"1631093","PLAYER_NAME":"Jaden Ivey","SEASON":"2023-24","SHOT_ZONE_BASIC":"In The Paint (Non-RA)","actual_points":170,"actual_points_per_shot":0.7798,"league_expected_pps":0.9414,"player_expected_pps":0.7543,"shot_making_per_100":-16.163,"player_adjusted_edge_per_100":-18.7176},{"PLAYER_ID":"1631093","PLAYER_NAME":"Jaden Ivey","SEASON":"2023-24","SHOT_ZONE_BASIC":"Left Corner 3","actual_points":45,"actual_points_per_shot":0.8333,"league_expected_pps":1.2421,"player_expected_pps":1.1352,"shot_making_per_100":-40.8803,"player_adjusted_edge_per_100":-10.6889},{"PLAYER_ID":"1631093","PLAYER_NAME":"Jaden Ivey","SEASON":"2023-24","SHOT_ZONE_BASIC":"Mid-Range","actual_points":72,"actual_points_per_shot":0.7579,"league_expected_pps":0.8917,"player_expected_pps":0.7345,"shot_making_per_100":-13.3847,"player_adjusted_edge_per_100":-15.722},{"PLAYER_ID":"1631093","PLAYER_NAME":"Jaden Ivey","SEASON":"2023-24","SHOT_ZONE_BASIC":"Restricted Area","actual_points":344,"actual_points_per_shot":1.1821,"league_expected_pps":1.3068,"player_expected_pps":1.1425,"shot_making_per_100":-12.4692,"player_adjusted_edge_per_100":-16.4331},{"PLAYER_ID":"1631093","PLAYER_NAME":"Jaden Ivey","SEASON":"2023-24","SHOT_ZONE_BASIC":"Right Corner 3","actual_points":39,"actual_points_per_shot":1.3448,"league_expected_pps":1.2183,"player_expected_pps":1.0732,"shot_making_per_100":12.6538,"player_adjusted_edge_per_100":-14.513}]