[{"PLAYER_ID":"101108","PLAYER_NAME":"Chris Paul","SEASON":"2021-22","SHOT_ZONE_BASIC":"Above the Break 3","actual_points":174,"actual_points_per_shot":0.9721,"league_expected_pps":1.0988,"player_expected_pps":1.0889,"shot_making_per_100":-12.6726,"player_adjusted_edge_per_100":-0.9898},{"PLAYER_ID":"101108","PLAYER_NAME":"Chris Paul","SEASON":"2021-22","SHOT_ZONE_BASIC":"Backcourt","actual_points":0,"actual_points_per_shot":0.0,"league_expected_pps":0.2728,"player_expected_pps":0.1586,"shot_making_per_100":-27.2757,"player_adjusted_edge_per_100":-11.4118},{"PLAYER_ID":"101108","PLAYER_NAME":"Chris Paul","SEASON":"2021-22","SHOT_ZONE_BASIC":"In The Paint (Non-RA)","actual_points":252,"actual_points_per_shot":1.2057,"league_expected_pps":0.9551,"player_expected_pps":1.0518,"shot_making_per_100":25.0638,"player_adjusted_edge_per_100":9.6674},{"PLAYER_ID":"101108","PLAYER_NAME":"Chris Paul","SEASON":"2021-22","SHOT_ZONE_BASIC":"Left Corner 3","actual_points":9,"actual_points_per_shot":0.6923,"league_expected_pps":1.2137,"player_expected_pps":1.2632,"shot_making_per_100":-52.1433,"player_adjusted_edge_per_100":4.9441},{"PLAYER_ID":"101108","PLAYER_NAME":"Chris Paul","SEASON":"2021-22","SHOT_ZONE_BASIC":"Mid-Range","actual_points":308,"actual_points_per_shot":1.037,"league_expected_pps":0.923,"player_expected_pps":1.0062,"shot_making_per_100":11.408,"player_adjusted_edge_per_100":8.3232},{"PLAYER_ID":"101108","PLAYER_NAME":"Chris Paul","SEASON":"2021-22","SHOT_ZONE_BASIC":"Restricted Area","actual_points":40,"actual_points_per_shot":1.2903,"league_expected_pps":1.252,"player_expected_pps":1.3792,"shot_making_per_100":3.8277,"player_adjusted_edge_per_100":12.7191},{"PLAYER_ID":"101108","PLAYER_NAME":"Chris Paul","SEASON":"2021-22","SHOT_ZONE_BASIC":"Right Corner 3","actual_points":6,"actual_points_per_shot":1.5,"league_expected_pps":1.207,"player_expected_pps":1.1879,"shot_making_per_100":29.299,"player_adjusted_edge_per_100":-1.9083}]