[{"PLAYER_ID":"203507","PLAYER_NAME":"Giannis Antetokounmpo","SEASON":"2019-20","TEAM_ABBREVIATION":"MIL","AGE":25,"GP":63,"MIN":1916.88,"PTS":1857,"REB":856,"AST":354,"TS_PCT":0.613,"EFG_PCT":0.589,"USG_PCT":0.363,"NET_RATING":15.4,"PIE":0.239,"shots":1238,"actual_points_per_shot":1.1785,"league_expected_pps":1.251,"player_expected_pps":1.2472,"shot_making_per_100":-7.2458,"player_adjusted_edge_per_100":-0.3752},{"PLAYER_ID":"203507","PLAYER_NAME":"Giannis Antetokounmpo","SEASON":"2020-21","TEAM_ABBREVIATION":"MIL","AGE":26,"GP":61,"MIN":2012.7333,"PTS":1717,"REB":671,"AST":357,"TS_PCT":0.633,"EFG_PCT":0.6,"USG_PCT":0.32,"NET_RATING":9.8,"PIE":0.196,"shots":1100,"actual_points_per_shot":1.1991,"league_expected_pps":1.2511,"player_expected_pps":1.2442,"shot_making_per_100":-5.2024,"player_adjusted_edge_per_100":-0.6921},{"PLAYER_ID":"203507","PLAYER_NAME":"Giannis Antetokounmpo","SEASON":"2021-22","TEAM_ABBREVIATION":"MIL","AGE":27,"GP":67,"MIN":2204.225,"PTS":2002,"REB":778,"AST":388,"TS_PCT":0.633,"EFG_PCT":0.582,"USG_PCT":0.34,"NET_RATING":8.0,"PIE":0.21,"shots":1245,"actual_points_per_shot":1.1639,"league_expected_pps":1.2083,"player_expected_pps":1.2025,"shot_making_per_100":-4.4397,"player_adjusted_edge_per_100":-0.5776},{"PLAYER_ID":"203507","PLAYER_NAME":"Giannis Antetokounmpo","SEASON":"2022-23","TEAM_ABBREVIATION":"MIL","AGE":28,"GP":63,"MIN":2023.615,"PTS":1959,"REB":742,"AST":359,"TS_PCT":0.605,"EFG_PCT":0.572,"USG_PCT":0.373,"NET_RATING":7.2,"PIE":0.204,"shots":1278,"actual_points_per_shot":1.1432,"league_expected_pps":1.2654,"player_expected_pps":1.274,"shot_making_per_100":-12.2195,"player_adjusted_edge_per_100":0.8596},{"PLAYER_ID":"203507","PLAYER_NAME":"Giannis Antetokounmpo","SEASON":"2023-24","TEAM_ABBREVIATION":"MIL","AGE":29,"GP":73,"MIN":2567.2433,"PTS":2222,"REB":841,"AST":476,"TS_PCT":0.649,"EFG_PCT":0.624,"USG_PCT":0.32,"NET_RATING":6.6,"PIE":0.197,"shots":1369,"actual_points_per_shot":1.2476,"league_expected_pps":1.2915,"player_expected_pps":1.3226,"shot_making_per_100":-4.3905,"player_adjusted_edge_per_100":3.1042},{"PLAYER_ID":"203507","PLAYER_NAME":"Giannis Antetokounmpo","SEASON":"2024-25","TEAM_ABBREVIATION":"MIL","AGE":30,"GP":67,"MIN":2288.63,"PTS":2036,"REB":798,"AST":433,"TS_PCT":0.625,"EFG_PCT":0.607,"USG_PCT":0.346,"NET_RATING":7.2,"PIE":0.21,"shots":1319,"actual_points_per_shot":1.213,"league_expected_pps":1.253,"player_expected_pps":1.2939,"shot_making_per_100":-4.0004,"player_adjusted_edge_per_100":4.0859}]