[{"PLAYER_ID":"1629001","PLAYER_NAME":"De'Anthony Melton","SEASON":"2021-22","SHOT_ZONE_BASIC":"Above the Break 3","actual_points":326,"actual_points_per_shot":1.0619,"league_expected_pps":1.1053,"player_expected_pps":1.0645,"shot_making_per_100":-4.3394,"player_adjusted_edge_per_100":-4.0814},{"PLAYER_ID":"1629001","PLAYER_NAME":"De'Anthony Melton","SEASON":"2021-22","SHOT_ZONE_BASIC":"Backcourt","actual_points":0,"actual_points_per_shot":0.0,"league_expected_pps":0.0379,"player_expected_pps":0.038,"shot_making_per_100":-3.7933,"player_adjusted_edge_per_100":0.0058},{"PLAYER_ID":"1629001","PLAYER_NAME":"De'Anthony Melton","SEASON":"2021-22","SHOT_ZONE_BASIC":"In The Paint (Non-RA)","actual_points":92,"actual_points_per_shot":0.7797,"league_expected_pps":0.9151,"player_expected_pps":0.7606,"shot_making_per_100":-13.5474,"player_adjusted_edge_per_100":-15.4556},{"PLAYER_ID":"1629001","PLAYER_NAME":"De'Anthony Melton","SEASON":"2021-22","SHOT_ZONE_BASIC":"Left Corner 3","actual_points":54,"actual_points_per_shot":1.7419,"league_expected_pps":1.2099,"player_expected_pps":1.2396,"shot_making_per_100":53.2054,"player_adjusted_edge_per_100":2.967},{"PLAYER_ID":"1629001","PLAYER_NAME":"De'Anthony Melton","SEASON":"2021-22","SHOT_ZONE_BASIC":"Mid-Range","actual_points":36,"actual_points_per_shot":0.5625,"league_expected_pps":0.8507,"player_expected_pps":0.7268,"shot_making_per_100":-28.8182,"player_adjusted_edge_per_100":-12.3854},{"PLAYER_ID":"1629001","PLAYER_NAME":"De'Anthony Melton","SEASON":"2021-22","SHOT_ZONE_BASIC":"Restricted Area","actual_points":154,"actual_points_per_shot":1.1,"league_expected_pps":1.3824,"player_expected_pps":1.2298,"shot_making_per_100":-28.2437,"player_adjusted_edge_per_100":-15.267},{"PLAYER_ID":"1629001","PLAYER_NAME":"De'Anthony Melton","SEASON":"2021-22","SHOT_ZONE_BASIC":"Right Corner 3","actual_points":39,"actual_points_per_shot":1.2188,"league_expected_pps":1.2279,"player_expected_pps":1.0982,"shot_making_per_100":-0.9152,"player_adjusted_edge_per_100":-12.9731}]